dcex/__init__.py
dcex/async_support/__init__.py
dcex/async_support/binance/__init__.py
dcex/async_support/binance/_account_http.py
dcex/async_support/binance/_http_manager.py
dcex/async_support/binance/_market_http.py
dcex/async_support/binance/_trade_http.py
dcex/async_support/binance/client.py
dcex/async_support/binance/enums.py
dcex/async_support/binance/endpoints/account.py
dcex/async_support/binance/endpoints/market.py
dcex/async_support/binance/endpoints/trade.py
dcex/async_support/bingx/__init__.py
dcex/async_support/bingx/_account_http.py
dcex/async_support/bingx/_http_manager.py
dcex/async_support/bingx/_market_http.py
dcex/async_support/bingx/_trade_http.py
dcex/async_support/bingx/client.py
dcex/async_support/bingx/endpoints/account.py
dcex/async_support/bingx/endpoints/market.py
dcex/async_support/bingx/endpoints/trade.py
dcex/async_support/bitmart/__init__.py
dcex/async_support/bitmart/_account_http.py
dcex/async_support/bitmart/_http_manager.py
dcex/async_support/bitmart/_market_http.py
dcex/async_support/bitmart/_trade_http.py
dcex/async_support/bitmart/client.py
dcex/async_support/bitmart/endpoints/account.py
dcex/async_support/bitmart/endpoints/market.py
dcex/async_support/bitmart/endpoints/trade.py
dcex/async_support/bitmex/__init__.py
dcex/async_support/bitmex/_account_http.py
dcex/async_support/bitmex/_http_manager.py
dcex/async_support/bitmex/_market_http.py
dcex/async_support/bitmex/_position_http.py
dcex/async_support/bitmex/_trade_http.py
dcex/async_support/bitmex/_trading_http.py
dcex/async_support/bitmex/client.py
dcex/async_support/bitmex/endpoints/funds.py
dcex/async_support/bitmex/endpoints/market.py
dcex/async_support/bitmex/endpoints/order.py
dcex/async_support/bitmex/endpoints/positions.py
dcex/async_support/bitmex/endpoints/trading.py
dcex/async_support/bybit/__init__.py
dcex/async_support/bybit/_account_http.py
dcex/async_support/bybit/_asset_http.py
dcex/async_support/bybit/_http_manager.py
dcex/async_support/bybit/_market_http.py
dcex-0.9.2.dist-info/licenses/LICENSE
dcex-0.9.2.dist-info/METADATA
dcex-0.9.2.dist-info/WHEEL
dcex-0.9.2.dist-info/top_level.txt
dcex-0.9.2.dist-info/RECORD
