Metadata-Version: 2.4
Name: dcex
Version: 0.9.2
Summary: A Lightweight Python Package for Low-Latency and Cross-Exchange Trading.
Author: pg56714
License-Expression: MIT
Project-URL: Repository, https://github.com/pg56714/dcex
Classifier: Development Status :: 4 - Beta
Classifier: Intended Audience :: Developers
Classifier: Intended Audience :: Financial and Insurance Industry
Classifier: Topic :: Office/Business :: Financial
Classifier: Topic :: Software Development :: Libraries :: Python Modules
Classifier: Programming Language :: Python :: 3
Classifier: Programming Language :: Python :: 3.12
Classifier: Operating System :: OS Independent
Requires-Python: >=3.12
License-File: LICENSE
Requires-Dist: httpx>=0.28.1
Requires-Dist: polars>=1.34.0
Requires-Dist: requests>=2.32.5
Requires-Dist: msgspec>=0.19.0
Requires-Dist: coincurve>=21.0.0
Requires-Dist: pycryptodome>=3.23.0
Dynamic: license-file
